git_gerrit/__init__.py
git_gerrit/__version__.py
git_gerrit/cli.py
git_gerrit/core.py
git_gerrit/db.py
git_gerrit/error.py
git_gerrit/git.py
git_gerrit/spinner.py
git_gerrit-3.0.0.dist-info/licenses/LICENSE.txt
git_gerrit-3.0.0.dist-info/METADATA
git_gerrit-3.0.0.dist-info/WHEEL
git_gerrit-3.0.0.dist-info/entry_points.txt
git_gerrit-3.0.0.dist-info/top_level.txt
git_gerrit-3.0.0.dist-info/RECORD
