Metadata-Version: 2.4
Name: git_gerrit
Version: 3.0.0
Summary: Gerrit review system command line tools.
Home-page: https://github.com/meffie/git-gerrit
Author: Michael Meffie
Author-email: mmeffie@sinenomine.net
License: BSD-2-Clause
Classifier: Development Status :: 4 - Beta
Classifier: Environment :: Console
Classifier: Intended Audience :: Developers
Classifier: Operating System :: POSIX
Classifier: Programming Language :: Python :: 3
Classifier: Topic :: Software Development
License-File: LICENSE.txt
Requires-Dist: sh
Requires-Dist: pygerrit2
Dynamic: author
Dynamic: author-email
Dynamic: classifier
Dynamic: description
Dynamic: home-page
Dynamic: license
Dynamic: license-file
Dynamic: requires-dist
Dynamic: summary
